Metadata-Version: 1.2
Name: u2py
Version: 1.0
Summary: A utility to convert ui files to python files
Home-page: https://github.com/dragneelfps/project-u2py
Author: Sourabh S. Rawat
Author-email: dragneelfps@gmail.com
License: GPLv3+
Platform: UNKNOWN
Classifier: Development Status :: 4 - Beta
Classifier: Intended Audience :: Developers
Classifier: Topic :: Software Development :: Build Tools
Classifier: License :: OSI Approved :: GNU General Public License v3 or later (GPLv3+)
Classifier: Programming Language :: Python :: 3.5
Classifier: Programming Language :: Python :: 3.6
Classifier: Natural Language :: English
Classifier: Operating System :: Microsoft :: Windows :: Windows 10
Requires-Python: >=3
